{
    "s3 url path": null,
    "site": "jobkorea",
    "id": "45773553",
    "collection_date": "2024-11-23",
    "deadline": "2024-11-30",
    "search": "데이터 엔지니어",
    "company": "브래키츠㈜",
    "post title": "브래키츠㈜\n기업인증 완료\n관심기업\n관심기업 추가하고 채용소식 받기\n닫기\n[브래키츠] SAP BW 경력직",
    "url": "https://www.jobkorea.co.kr/Recruit/GI_Read/45773553?Oem_Code=C1&logpath=1&stext=%EB%8D%B0%EC%9D%B4%ED%84%B0%20%EC%97%94%EC%A7%80%EB%8B%88%EC%96%B4&listno=782",
    "image": [],
    "text": "SAP BW 경력직 \n포지션 및 자격요건\nSAP BW 경력직\n( 0명 )\n기업정보      \n            \n\n업           력 : 4년차 (2021년 3월 설립)\n주           소 : 서울특별시 중구 청계천로 100 9층\n주요 서비스 : SAP ERP, BI, SailPoint, IT Consulting\n홈  페 이 지 : www.brackets.solutions \n\n회사소개\n‘디지털 해결소’를 표방하는 브래키츠㈜는 다양한 분야의 유수 고객사에 Analytics, Cloud 등 Digital Transformation 기반 컨설팅 서비스와 ERP, BI 등 기업핵심 솔루션을 제공하는 IT 서비스 기업입니다. 2021년 창사 이래 지속적인 성장을 하고 있으며 특히 기업가치에 기반을 둔 서비스 제공과 보다 나은 솔루션 제공을 위해 열정 있는 인재들과 함께 지속 성장을 도모하고자 합니다. 저희 브래키츠에서 미래 가치성장에 기반을 둔 역량과 커리어의 발전을 함께하세요.\n 기술스택\nSAP BASIS, ABAP, Tableau, SailPoint, Java, Python, Cloud, BI, DataSphere\n\n주요업무\n●   SAP Datasphere, SAP BW 등 DW/BW 설계 및 구축\n●   SAP SAC, Tableau, Power BI 등 Self BI 시각화 개발 \n\n자격요건\n●   BW 경험 있는 중간 리더급 경력자\n●   시스템 구축 프로젝트 PL  또는 개발관리 경험자\n●   Self BI Tool  사용 유경험자  \n●   Data Warehouse, Datamart 구축 프로젝트 경험자\n\n우대사항\n●   분석계/정보계 관련 리딩 경력 또는 경험 보유\n●   SAP BW, SAP Datasphere, SAP SAC 관련 경험이 있으신 분  \n●   SAC, Tableau, Power BI 등 Self BI Tool 활용한 지표 개발 및 분석 경험이 있으신 분 \n\n\n복지/혜택\n[충분한 휴식은 업무의 밑거름]\n●   자유로운 연차 사용 독려 (휴가는 승인이 아닌 통보)\n●   법정 연차 준수는 철저히\n●   거리가 먼 분들을 위해 유연한 출/퇴근 시간제 적용\n [개인의 성장은 곧 회사의 성장]\n●   교육비 지원\n●   자격증 취득 지원\n●   도서구입비 지원\n\n [사람이 가장 소중한 회사]\n●   장기근속자 포상 \n●   지인 추천 시 포상금 지급 \n●   사업기여 포상금 지급 \n●   프리미엄 건강검진 제공 \n\n[회사와 함께하는 작은 기쁨]\n●   연 1회 이상 전 직원 Workshop\n [당신과 함께하는 근무 환경]\n●   8시 ~ 10시 탄력 출퇴근제 적용\n●   무제한 스낵바 & 고급 커피머신\n●   최신 노트북 & 모니터 지급\n●   조직별 월 1회 이상 회식, 그러나 참석은 자유\n \n채용절차\n●   서류전형 > 1차 면접(실무진) > 2차 면접(임원) > 최종합격\n   브래키츠(주)는 열정 있고 도전적인 인재와 함께 SAP BW, Tableau 및 다양한 BI 관련 프로젝트를 추진함으로써 회사의 성장 뿐만 아니라 고객사, 나아가 비즈니스 업계의 성장에 일조하고자 합니다. 관심 있는 경력자 분들의 많은 관심과 지원을 기대합니다.\n\n전형절차\nㆍ서류전형 > 1차면접 > 2차면접  > 최종합격\nㆍ면접일정은 추후 통보됩니다.\n\n유의사항\nㆍ허위사실이 발견될 경우 채용이 취소될 수 있습니다."
}