{
    "s3 url path": null,
    "site": "jobkorea",
    "id": "45966486",
    "collection_date": "2024-11-23",
    "deadline": "2024-12-20",
    "search": "데이터 엔지니어",
    "company": "삼양데이타시스템㈜",
    "post title": "삼양데이타시스템㈜\n기업인증 완료\n관심기업\n관심기업 추가하고 채용소식 받기\n닫기\n서버 운영 경력사원 채용",
    "url": "https://www.jobkorea.co.kr/Recruit/GI_Read/45966486?Oem_Code=C1&logpath=1&stext=%EB%8D%B0%EC%9D%B4%ED%84%B0%20%EC%97%94%EC%A7%80%EB%8B%88%EC%96%B4&listno=747",
    "image": [],
    "text": "서버 운영 경력사원 채용\n삼양데이타시스템㈜는 1995년에 설립된 회사로 자본금 30억원, 매출액 778억 8,416만원, 사원수 171명 규모의 중견기업입니다. 서울 종로구 종로33길 31 (연지동, 삼양사)에 위치하고 있으며, S/W개발,IT아웃소싱,영상회의,정보보호,자격증사업을 하고 있습니다.\n포지션 및 자격요건\n서버운영\n( ○명 )\n담당업무\nㆍx86 OS(Linux, Windows) 운영\nㆍ가상화(VMWare, HCI) 운영\nㆍ계정/접근제어 운영 및 관리\nㆍEMS : 시스템 모니터링 성능 솔루션 운영 및 관리\nㆍ백업 SW 운영\n\n자격요건\nㆍ학력 : 학력무관\nㆍ경력 : 경력7년↑\n\n우대사항\nㆍ유관업무 경력자\nㆍ장애인\nㆍ보훈대상자\n\n전형절차\nㆍ서류전형 > 1차면접 > 2차면접 > 최종합격\nㆍ면접일정은 추후 통보됩니다.\n\n유의사항\nㆍ허위사실이 발견될 경우 채용이 취소될 수 있습니다."
}